[
    {
        "category": "List of Requests",
        "subcategory": "Persona 4",
        "name": "Acquire an Angel Statue",
        "id": "1",
        "quest_giver": "Timid Female Student, Classroom 2-2",
        "available": "5/2",
        "reward": "Chest Key x3",
        "remarks": "Dropped by Avenger Knight, Yukiko's Castle (6F-7F)",
        "sortOrder": 0
    },
    {
        "category": "List of Requests",
        "subcategory": "Persona 4",
        "name": "Acquire a Demon Statue",
        "id": "2",
        "quest_giver": "Shady Student, 2nd Floor Hallway",
        "available": "5/2",
        "reward": "Dokudami Tea x3",
        "remarks": "Dropped by Magical Magus, Yukiko's Castle (6F-7F)",
        "sortOrder": 1
    },
    {
        "category": "List of Requests",
        "subcategory": "Persona 4",
        "name": "The Girl on the Rooftop",
        "id": "3",
        "quest_giver": "Male student by the window, Classroom 2-2",
        "available": "4/25",
        "reward": "Goho-M",
        "remarks": "Talk to the girl on the roof 3 times; can only ask one question per day.",
        "sortOrder": 2
    },
    {
        "category": "List of Requests",
        "subcategory": "Persona 4",
        "name": "Acquire a Ritz Wire",
        "id": "4",
        "quest_giver": "Male student near Science Room, Practice Building 1F",
        "available": "5/2",
        "reward": "Olympic Tape",
        "remarks": "Dropped by Heat Balance, Yukiko's Castle (6F-7F)",
        "sortOrder": 3
    },
    {
        "category": "List of Requests",
        "subcategory": "Persona 4",
        "name": "Acquire Mori Ranmaru Shochu",
        "id": "5",
        "quest_giver": "Man to the west, Samegawa Flood Plain",
        "available": "5/1",
        "reward": "¥4,000",
        "remarks": "Check sake barrels in the Twisted Shopping District's version of Konishi Liquors",
        "sortOrder": 4
    },
    {
        "category": "List of Requests",
        "subcategory": "Persona 4",
        "name": "I Wish for Love",
        "id": "6",
        "quest_giver": "Fox",
        "available": "5/6",
        "reward": "Hermit Social Link Up",
        "remarks": "Talk to the girl on 3 different days, in the school lobby, then Practice Building 2F (select \"I read it\") twice",
        "sortOrder": 5
    },
    {
        "category": "List of Requests",
        "subcategory": "Persona 4",
        "name": "Desk Refurbishing",
        "id": "7",
        "quest_giver": "Homely Student, Biology Lab",
        "available": "5/18",
        "reward": "Royal Jelly x5",
        "remarks": "Dropped by Laughing Table, Yukiko's Castle (6F-7F)",
        "sortOrder": 6
    },
    {
        "category": "List of Requests",
        "subcategory": "Persona 4",
        "name": "Book Exchange",
        "id": "8",
        "quest_giver": "Avid reader in front of Yomenaido Bookstore",
        "available": "5/23",
        "reward": "The Gentle Way (book)",
        "remarks": "Give him a Peach Seed",
        "sortOrder": 7
    },
    {
        "category": "List of Requests",
        "subcategory": "Persona 4",
        "name": "Acquire an Old Key",
        "id": "9",
        "quest_giver": "Old Woman, Samegawa Flood Plain",
        "available": "6/5",
        "reward": "Knowledge + Courage Up",
        "remarks": "Dropped by Bribed Fuzz, Steamy Bathhouse (1F-2F)",
        "sortOrder": 8
    },
    {
        "category": "List of Requests",
        "subcategory": "Persona 4",
        "name": "Extracurricular Activities",
        "id": "10",
        "quest_giver": "Ms. Sofue, 2nd Floor Hallway",
        "available": "5/18",
        "reward": "Pulsating Stone x2",
        "remarks": "Dropped by Trance Twins, Yukiko's Castle (3F-5F)",
        "sortOrder": 9
    },
    {
        "category": "List of Requests",
        "subcategory": "Persona 4",
        "name": "Acquire Coal",
        "id": "11",
        "quest_giver": "Loud Old Man, Shopping District North",
        "available": "6/5",
        "reward": "¥15,000",
        "remarks": "Dropped by Selfish Basalt, Steamy Bathhouse (7F-8F)",
        "sortOrder": 10
    },
    {
        "category": "List of Requests",
        "subcategory": "Persona 4",
        "name": "Desk Refurbishing Part 2",
        "id": "12",
        "quest_giver": "Homely Student, Practice Building 2F",
        "available": "6/7",
        "reward": "Snuff Soul x2",
        "remarks": "Dropped by Crying Table, Steamy Bathhouse (9F-10F)",
        "sortOrder": 11
    },
    {
        "category": "List of Requests",
        "subcategory": "Persona 4",
        "name": "I Wish I Didn't Crave for Snacks",
        "id": "13",
        "quest_giver": "Fox",
        "available": "5/6, Complete #6",
        "reward": "Hermit Social Link Up",
        "remarks": "Talk to Slim Lady, Shopping District South; get Meat Gum from Chie and give to Slim Lady",
        "sortOrder": 12
    },
    {
        "category": "List of Requests",
        "subcategory": "Persona 4",
        "name": "Please Feed the Cat",
        "id": "14",
        "quest_giver": "Avid reader in front of Yomenaido Bookstore",
        "available": "6/3, Complete #8",
        "reward": "The Punk's Way (book)",
        "remarks": "Feed the cat one fish",
        "sortOrder": 13
    },
    {
        "category": "List of Requests",
        "subcategory": "Persona 4",
        "name": "Acquire a Crooked Cross",
        "id": "15",
        "quest_giver": "Timid Female Student, Classroom 2-2",
        "available": "6/7, Complete #1",
        "reward": "Ointment x3",
        "remarks": "Dropped by Tranquil Idol, Steamy Bathhouse (7F-8F)",
        "sortOrder": 14
    },
    {
        "category": "List of Requests",
        "subcategory": "Persona 4",
        "name": "Acquire a Horn",
        "id": "16",
        "quest_giver": "Housewife, Shopping District South",
        "available": "6/9",
        "reward": "¥18,000",
        "remarks": "Dropped by Grave Beetle, Steamy Bathhouse (9F-10F)",
        "sortOrder": 15
    },
    {
        "category": "List of Requests",
        "subcategory": "Persona 4",
        "name": "Please Find my Younger Twin",
        "id": "17",
        "quest_giver": "Orange haired girl, Shopping District South",
        "available": "6/9",
        "reward": "Goho-M x5",
        "remarks": "Talk to her twin on Samegawa Flood Plain, then return",
        "sortOrder": 16
    },
    {
        "category": "List of Requests",
        "subcategory": "Persona 4",
        "name": "Carbon Copy",
        "id": "18",
        "quest_giver": "Orange haired girl, Samagawa Flood Plain",
        "available": "7/13",
        "reward": "Value Medicine x3",
        "remarks": "Dropped by Soul Dancer, Marukyu Striptease (1F-3F)",
        "sortOrder": 17
    },
    {
        "category": "List of Requests",
        "subcategory": "Persona 4",
        "name": "Acquire a Silver Lump",
        "id": "19",
        "quest_giver": "Male student near Science Room, Practice Building 1F",
        "available": "6/30, Complete #4",
        "reward": "Uplifting Radio x2",
        "remarks": "Dropped by Silver Dice, Marukyu Striptease (7F-10F)",
        "sortOrder": 18
    },
    {
        "category": "List of Requests",
        "subcategory": "Persona 4",
        "name": "We Wish our Dog Would Return",
        "id": "20",
        "quest_giver": "Fox",
        "available": "5/6, Complete #13",
        "reward": "Hermit Social Link Up",
        "remarks": "Talk gently to the dog at the Riverbed and Shopping District North until it can be fed a Steak Skewer (buy at Souzai Daigaku)",
        "sortOrder": 19
    },
    {
        "category": "List of Requests",
        "subcategory": "Persona 4",
        "name": "Acquire a Charmed Veil",
        "id": "21",
        "quest_giver": "Timid Female Student, Classroom 2-2",
        "available": "7/12, Complete #15",
        "reward": "Chest Key x5",
        "remarks": "Dropped by Liberating Idol, Marukyu Striptease (5F-10F)",
        "sortOrder": 20
    },
    {
        "category": "List of Requests",
        "subcategory": "Persona 4",
        "name": "Acquire Hard Boots",
        "id": "22",
        "quest_giver": "Avid reader in front of Yomenaido Bookstore",
        "available": "7/3, Complete #14",
        "reward": "¥5,000\nGuide to Pests (book)",
        "remarks": "Buy from Daidara Metalworks (Sell Thick Hide x10)",
        "sortOrder": 21
    },
    {
        "category": "List of Requests",
        "subcategory": "Persona 4",
        "name": "Who's the Riddle Master?!",
        "id": "23",
        "quest_giver": "Funky Student, 3rd Floor Hallway",
        "available": "4/18",
        "reward": "Chest Key x3",
        "remarks": "\"Group A,\" \"Top 6 Flag Colors\"",
        "sortOrder": 22
    },
    {
        "category": "List of Requests",
        "subcategory": "Persona 4",
        "name": "Acquire an Eternal Lamp",
        "id": "24",
        "quest_giver": "Refreshed old man, Samegawa Flood Plain",
        "available": "8/22",
        "reward": "¥30,000",
        "remarks": "Dropped by Amenti Raven, Void Quest (3F-4F)",
        "sortOrder": 23
    },
    {
        "category": "List of Requests",
        "subcategory": "Persona 4",
        "name": "Feed the Cat",
        "id": "25",
        "quest_giver": "Cat, Samegawa Flood Plain",
        "available": "6/3, Complete #14",
        "reward": "Antibiotic Gel",
        "remarks": "Feed the cat fish once a day for 7 days",
        "sortOrder": 24
    },
    {
        "category": "List of Requests",
        "subcategory": "Persona 4",
        "name": "I Wish I Had Friends",
        "id": "26",
        "quest_giver": "Fox",
        "available": "5/6, Complete #20",
        "reward": "Hermit Social Link Up",
        "remarks": "Talk to the boy on Samegawa Flood Plain (\"I don't want your money\"); give him a Prize Sticker earned by buying from Tanaka's Amazing Commodities; talk to him again, then get a sticker from Nanako to give him, then talk to him the following day",
        "sortOrder": 25
    },
    {
        "category": "List of Requests",
        "subcategory": "Persona 4",
        "name": "Acquire Some Fashionable Dishes",
        "id": "27",
        "quest_giver": "Avid reader in front of Yomenaido Bookstore",
        "available": "8/9, Complete #22",
        "reward": "¥10,000\nRiddlemania (book)",
        "remarks": "Dropped by Sky Balance, Marukyu Striptease (9F-10F), 3 needed",
        "sortOrder": 26
    },
    {
        "category": "List of Requests",
        "subcategory": "Persona 4",
        "name": "Carbon Copy, Part 2",
        "id": "28",
        "quest_giver": "Riverbed Twin",
        "available": "8/22, Complete #18",
        "reward": "Macca Leaf x3",
        "remarks": "Dropped by Blind Cupid, Void Quest (3F-4F)",
        "sortOrder": 27
    },
    {
        "category": "List of Requests",
        "subcategory": "Persona 4",
        "name": "Experiment in Telepathy",
        "id": "29",
        "quest_giver": "Older twin",
        "available": "9/5",
        "reward": "Dokudami Tea x5",
        "remarks": "Talk to the Older twin in Shopping District, South, then talk to the Younger twin on the Samegawa Riverbed and pick the first choice, come back and talk to the Older twin",
        "sortOrder": 28
    },
    {
        "category": "List of Requests",
        "subcategory": "Persona 4",
        "name": "I Wish My Life Had Meaning Again",
        "id": "30",
        "quest_giver": "Fox",
        "available": "5/6, Complete #26",
        "reward": "Hermit Social Link Up\nUnfinished Model",
        "remarks": "Talk to the Haggard Man, Shopping District North (\"Want me to make it?\"); build the Unfinished Model over 4 days, then give it to him",
        "sortOrder": 29
    },
    {
        "category": "List of Requests",
        "subcategory": "Persona 4",
        "name": "Extracurricular Activities, Part 2",
        "id": "31",
        "quest_giver": "Ms. Sofue, 2nd Floor Hallway",
        "available": "9/20, Complete #10",
        "reward": "Mystical Scarab x2",
        "remarks": "Dropped by Steel Machine, Void Quest (9F-10F)",
        "sortOrder": 30
    },
    {
        "category": "List of Requests",
        "subcategory": "Persona 4",
        "name": "Acquire a Crystal Ball",
        "id": "32",
        "quest_giver": "Mrs. Nakayama, 3rd Floor Hallway",
        "available": "10/8",
        "reward": "¥35,000",
        "remarks": "Dropped by Constancy Relic, Secret Laboratory (1F-2F)",
        "sortOrder": 31
    },
    {
        "category": "List of Requests",
        "subcategory": "Persona 4",
        "name": "Acquire Fine Coal",
        "id": "33",
        "quest_giver": "Loud Old Man, Shopping District North",
        "available": "10/9, Complete #11",
        "reward": "¥40,000",
        "remarks": "Dropped by Power Castle, Secret Laboratory (7F-8F)",
        "sortOrder": 32
    },
    {
        "category": "List of Requests",
        "subcategory": "Persona 4",
        "name": "A Test of Literary Memory",
        "id": "34",
        "quest_giver": "Avid reader in front of Yomenaido Bookstore",
        "available": "9/26, Complete #27",
        "reward": "Who Am I? (book)",
        "remarks": "\"Judo Medalist Names,\" \"How one should live as a punk,\" \"2 pages per pest,\" \"Me\"",
        "sortOrder": 33
    },
    {
        "category": "List of Requests",
        "subcategory": "Persona 4",
        "name": "Desk Refurbishing, Part 3",
        "id": "35",
        "quest_giver": "Homely Student, Practice Building 2F",
        "available": "9/29, Complete #12",
        "reward": "Bead",
        "remarks": "Dropped by Furious Gigas, Secret Laboratory (3F-4F)",
        "sortOrder": 34
    },
    {
        "category": "List of Requests",
        "subcategory": "Persona 4",
        "name": "I Wish I Was Better at Speaking",
        "id": "36",
        "quest_giver": "Fox",
        "available": "5/6, Complete #30, Understanding Rank 3+",
        "reward": "Hermit Social Link Up",
        "remarks": "Talk to the girl on the roof; \"Do you need help speaking?\", \"Give her lessons\" (Expression Rank 3+), then \"Apologize to her\" (Courage Rank 3+)",
        "sortOrder": 35
    },
    {
        "category": "List of Requests",
        "subcategory": "Persona 4",
        "name": "Acquire a High-Speed Gear",
        "id": "37",
        "quest_giver": "Girl in glasses, 1st Floor Hallway",
        "available": "10/8",
        "reward": "Physical Mirror x3",
        "remarks": "Dropped by Mach Wheel, Secret Laboratory (5F-6F)",
        "sortOrder": 36
    },
    {
        "category": "List of Requests",
        "subcategory": "Persona 4",
        "name": "A Twin's Independence",
        "id": "38",
        "quest_giver": "Riverbed Twin",
        "available": "10/9, Complete #28",
        "reward": "Bead Chain",
        "remarks": "Dropped by Elegant Mother, Secret Laboratory (7F-8F)",
        "sortOrder": 37
    },
    {
        "category": "List of Requests",
        "subcategory": "Persona 4",
        "name": "Acquire a Training Shell",
        "id": "39",
        "quest_giver": "Principal, 3rd Floor Hallway",
        "available": "10/8",
        "reward": "Understanding + Diligence Up",
        "remarks": "Dropped by Wicked Turret, Secret Laboratory (7F-8F)",
        "sortOrder": 38
    },
    {
        "category": "List of Requests",
        "subcategory": "Persona 4",
        "name": "Experiments in Telepathy, Part 2",
        "id": "40",
        "quest_giver": "Bookstore Twin",
        "available": "10/31, Complete #29",
        "reward": "Super Sonic x3",
        "remarks": "Speak to the Riverbed Twin, then the Bookstore Twin; repeat",
        "sortOrder": 39
    },
    {
        "category": "List of Requests",
        "subcategory": "Persona 4",
        "name": "I Wish I Didn't Fear Cats",
        "id": "41",
        "quest_giver": "Fox",
        "available": "5/6, Complete #14, #36",
        "reward": "Hermit Social Link Up",
        "remarks": "Talk to the fearful man at Samegawa Flood Plain (\"Is it a cat?\"), then talk to the cat outside the Dojima Residence, and bring the man to see the cat; give the man a Red Goldfish, then talk to him the next day",
        "sortOrder": 40
    },
    {
        "category": "List of Requests",
        "subcategory": "Persona 4",
        "name": "I Wish My Wallet Would Return",
        "id": "42",
        "quest_giver": "Fox",
        "available": "5/6, Complete #41",
        "reward": "Hermit Social Link Up",
        "remarks": "Talk to the woman near the trash can, Samegawa Flood Plain; check the area to find the wrong wallet and try to give it to her; find her wallet in the bushes near Tatsuhime Shrine and give it to her",
        "sortOrder": 41
    },
    {
        "category": "List of Requests",
        "subcategory": "Persona 4",
        "name": "The Girl on the Rooftop, Part 2",
        "id": "43",
        "quest_giver": "Male student by the window, Classroom 2-2",
        "available": "11/22, Complete #3",
        "reward": "Mokoi Doll",
        "remarks": "Dropped by Prime Magus, Heaven (1F-2F)",
        "sortOrder": 42
    },
    {
        "category": "List of Requests",
        "subcategory": "Persona 4",
        "name": "Desk Refurbishing, Part 4",
        "id": "44",
        "quest_giver": "Homely Student, Practice Building 2F",
        "available": "11/22, Complete #35",
        "reward": "Assault Signal x3",
        "remarks": "Dropped by Angry Table, Heaven (5F-7F)",
        "sortOrder": 43
    },
    {
        "category": "List of Requests",
        "subcategory": "Persona 4",
        "name": "Acquire an Old Ore",
        "id": "45",
        "quest_giver": "Male student near Science Room",
        "available": "11/22, Complete #19",
        "reward": "Spirit Radio",
        "remarks": "Dropped by Revelation Pesce, Heaven (6F-7F)",
        "sortOrder": 44
    },
    {
        "category": "List of Requests",
        "subcategory": "Persona 4",
        "name": "Acquire a Modest Lamp",
        "id": "46",
        "quest_giver": "Old Man, Riverbed",
        "available": "11/22, Complete #24",
        "reward": "¥45,000",
        "remarks": "Dropped by Phantom Lord, Heaven (3F-5F)",
        "sortOrder": 45
    },
    {
        "category": "List of Requests",
        "subcategory": "Persona 4",
        "name": "Riddle Senpai Returns!",
        "id": "47",
        "quest_giver": "Funky Student, 3rd Floor Hallway",
        "available": "9/2, Complete #23",
        "reward": "Snuff Soul",
        "remarks": "\"Group A,\" \"Human motion,\" \"Group B,\" \"Indefinite articles\"",
        "sortOrder": 46
    },
    {
        "category": "List of Requests",
        "subcategory": "Persona 4",
        "name": "I Wish to See Samegawa's Guardian",
        "id": "48",
        "quest_giver": "Fox",
        "available": "5/6, Complete #42",
        "reward": "Hermit Social Link Max",
        "remarks": "Catch a \"Huge Fish,\" bring to the Old Man and ask about the Guardian; use the Angler's Set to catch it (only found on rainy days or in December)",
        "sortOrder": 47
    },
    {
        "category": "List of Requests",
        "subcategory": "Persona 4",
        "name": "Cat Needs Food Badly",
        "id": "49",
        "quest_giver": "Cat",
        "available": "6/3, Complete #25",
        "reward": "Soma",
        "remarks": "Feed the cat fish on 20 different days, or 4 different days if fed the Guardian each time",
        "sortOrder": 48
    },
    {
        "category": "List of Requests",
        "subcategory": "Persona 4",
        "name": "Revenge of Riddle Senpai!",
        "id": "50",
        "quest_giver": "Funky Student, 3rd Floor Hallway",
        "available": "11/12, Complete #47",
        "reward": "Chewing Soul",
        "remarks": "\"Group B,\" \"The way they're drawn,\" \"Promethium,\" \"Need\"",
        "sortOrder": 49
    }
]